spaco/__init__.py
spaco/color.py
spaco/colorization.py
spaco/distance.py
spaco/logging.py
spaco/mapping.py
spaco/misc.py
spaco/scm.py
spaco/utils.py
spaco/external/__init__.py
spaco/external/lack.py
spaco_release-0.2.2.dist-info/LICENSE
spaco_release-0.2.2.dist-info/METADATA
spaco_release-0.2.2.dist-info/WHEEL
spaco_release-0.2.2.dist-info/top_level.txt
spaco_release-0.2.2.dist-info/RECORD
