Metadata-Version: 2.1
Name: spaco-release
Version: 0.2.2
Summary: Spaco: a comprehensive tool for coloring spatial data at single-cell resolution
Home-page: https://github.com/BrainStOrmics/Spaco
Author: Zehua Jing, Qianhua Zhu, Hailin Pan
Author-email: jingzehua@genomics.cn
License: GPL
Requires-Python: >=3.7
License-File: LICENSE
Requires-Dist: anndata >=0.8.0
Requires-Dist: colormath >=3.0.0
Requires-Dist: numpy >=1.18.0
Requires-Dist: pandas >=0.25.1
Requires-Dist: pyciede2000 ==0.0.21
Requires-Dist: scikit-image >=0.19.0
Requires-Dist: scikit-learn >=0.19.0
Requires-Dist: scipy >=1.10.0
Requires-Dist: typing-extensions >=4.0.0
Requires-Dist: umap-learn >=0.5.0
